{
  "users": [
    {
      "user_name": "Boold",
      "discord_user": "1_bb",
      "mac_address": "15:57:5e:78:e2:88",
      "end_date": "2030-1-1 23:59:59",
      "postion":"get_pixel_color(1385, 22)",
      "color":"(0, 0, 0)"
    },
    {
      "user_name": "Eldaly",
      "discord_user": "eldaly15",
      "mac_address": "0d:37:dd:74:d0:43",
      "end_date": "2030-1-1 23:59:59",
      "postion":"get_pixel_color(1751,70)",
      "color":"(170,0,0)"
    },
    {
      "user_name": "MV",
      "discord_user": "mv_exe",
      "mac_address": "b8:e3:8e:38:e0:80",
      "end_date": "2077-12-13 23:59:59",
      "postion":"get_pixel_color(1385, 22)",
      "color":"(0, 0, 0)"
    }
  ]
}
